localstored/__init__.py
localstored/core.py
localstored/utils.py
localstored-0.0.2.dist-info/METADATA
localstored-0.0.2.dist-info/WHEEL
localstored-0.0.2.dist-info/licenses/LICENSE
localstored-0.0.2.dist-info/RECORD
